fhy_core/__init__.py
fhy_core/constraint.py
fhy_core/error.py
fhy_core/identifier.py
fhy_core/memory_instance.py
fhy_core/py.typed
fhy_core/symbol_table.py
fhy_core/types.py
fhy_core/expression/__init__.py
fhy_core/expression/core.py
fhy_core/expression/parser.py
fhy_core/expression/pprint.py
fhy_core/expression/visitor.py
fhy_core/expression/passes/__init__.py
fhy_core/expression/passes/basic.py
fhy_core/expression/passes/sympy.py
fhy_core/expression/passes/z3.py
fhy_core/param/__init__.py
fhy_core/param/core.py
fhy_core/param/fundamental.py
fhy_core/utils/__init__.py
fhy_core/utils/dict_utils.py
fhy_core/utils/enum.py
fhy_core/utils/lattice.py
fhy_core/utils/poset.py
fhy_core/utils/stack.py
fhy_core-0.0.2.dist-info/LICENSE
fhy_core-0.0.2.dist-info/METADATA
fhy_core-0.0.2.dist-info/WHEEL
fhy_core-0.0.2.dist-info/top_level.txt
fhy_core-0.0.2.dist-info/RECORD
