Metadata-Version: 2.1
Name: fhy_core
Version: 0.0.2
Summary: Core utilities for the FhY compiler infrastructure.
Author-email: Christopher Priebe <cpriebe@ucsd.edu>
Maintainer-email: Christopher Priebe <cpriebe@ucsd.edu>
License: Copyright (c) 2024 FhY Developers
Project-URL: Homepage, https://github.com/actlab-fhy/FhY-core
Project-URL: Issues, https://github.com/actlab-fhy/FhY-core/issues
Keywords: Compiler
Classifier: Development Status :: 3 - Alpha
Classifier: Programming Language :: Python :: 3
Classifier: Programming Language :: Python :: 3.10
Classifier: Programming Language :: Python :: 3.11
Classifier: Programming Language :: Python :: 3.12
Classifier: Programming Language :: Python :: 3.13
Requires-Python: >=3.10
License-File: LICENSE
Requires-Dist: frozendict
Requires-Dist: networkx
Requires-Dist: sympy
Requires-Dist: z3-solver
Provides-Extra: dev
Requires-Dist: fhy-core[docs,lint,test,type] ; extra == 'dev'
Requires-Dist: tox ; extra == 'dev'
Provides-Extra: lint
Requires-Dist: ruff ; extra == 'lint'
Requires-Dist: pylint ; extra == 'lint'
Provides-Extra: test
Requires-Dist: pytest ; extra == 'test'
Requires-Dist: coverage ; extra == 'test'
Requires-Dist: pytest-xdist ; extra == 'test'
Provides-Extra: type
Requires-Dist: mypy ; extra == 'type'
